supply_wire/supply_wire.v
module supply_wire(A, B, C, f);
    input A, B, C;
    output f;

    supply0 gnd;
    supply1 vdd;

    wire t1, t2;

    nand G1 (t1, vdd, A, B);
    xor G2 (t2, C, gnd);
    and G3 (f, t1, t2);
    
endmodule

supply_wire/supply_wire_tb.v
module supply_wire_tb;

    reg [2:0] A;
    wire f;

    supply_wire uut (A[2], A[1], A[0], f);

    initial begin

        $dumpfile("supply_wire.vcd");
        $dumpvars(0, supply_wire_tb);
        $monitor(f, A);

        A = 3'o0;
        #5 A = 3'o1;
        #5 A = 3'o2;
        #5 A = 3'o3;
        #5 A = 3'o4;
        #5 A = 3'o5;
        #5 A = 3'o6;
        #5 A = 3'o7;
        #5 $finish;


    end

endmodule

supply_wire/supply_wire.vcd
$date
	Mon Jan  8 11:36:44 2024
$end
$version
	Icarus Verilog
$end
$timescale
	1s
$end
$scope module supply_wire_tb $end
$var wire 1 ! f $end
$var reg 3 " A [2:0] $end
$scope module uut $end
$var wire 1 # A $end
$var wire 1 $ B $end
$var wire 1 % C $end
$var wire 1 ! f $end
$var wire 1 & gnd $end
$var wire 1 ' t1 $end
$var wire 1 ( t2 $end
$var wire 1 ) vdd $end
$upscope $end
$upscope $end
$enddefinitions $end
$comment Show the parameter values. $end
$dumpall
$end
#0
$dumpvars
1)
0(
1'
0&
0%
0$
0#
b0 "
0!
$end
#5
1!
1(
1%
b1 "
#10
0!
0(
1$
0%
b10 "
#15
1!
1(
1%
b11 "
#20
0!
0(
1#
0$
0%
b100 "
#25
1!
1(
1%
b101 "
#30
0!
0'
0(
1$
0%
b110 "
#35
1(
1%
b111 "
