mux16to1/mux2to1.v
module mux2to1(out, in, sel);

    input [1:0]in;
    input sel;
    output out;

    wire t1, t2, t3;
    not G1 (t1, sel);
    and G2 (t2, in[0], t1);
    and G3 (t3, in[1], sel);
    or G4 (out, t2, t3);


endmodule

mux16to1/mux2to1_tb.v
module mux2to1_tb;

    reg in1, in2, sel;
    wire out;

    mux2to1 DUT (out, {in2, in1}, sel);

    initial
        begin
            $dumpfile("mux2to1.vcd");
            $dumpvars(0, mux2to1_tb);

            $monitor($time, "in2 = %b in1 = %b sel = %b out = %b", in2, in1, sel, out);

            #5 {in2, in1, sel} = 3'o0;
            #5 {in2, in1, sel} = 3'o1;
            #5 {in2, in1, sel} = 3'o2;
            #5 {in2, in1, sel} = 3'o3;
            #5 {in2, in1, sel} = 3'o4;
            #5 {in2, in1, sel} = 3'o5;
            #5 {in2, in1, sel} = 3'o6;
            #5 {in2, in1, sel} = 3'o7;

            #5 $finish;

        end

endmodule

mux16to1/mux2to1.vcd
$date
	Fri Mar 22 11:03:19 2024
$end
$version
	Icarus Verilog
$end
$timescale
	1s
$end
$scope module mux2to1_tb $end
$var wire 1 ! out $end
$var reg 1 " in1 $end
$var reg 1 # in2 $end
$var reg 1 $ sel $end
$scope module DUT $end
$var wire 2 % in [1:0] $end
$var wire 1 ! out $end
$var wire 1 $ sel $end
$var wire 1 & t1 $end
$var wire 1 ' t2 $end
$var wire 1 ( t3 $end
$upscope $end
$upscope $end
$enddefinitions $end
$comment Show the parameter values. $end
$dumpall
$end
#0
$dumpvars
x(
x'
x&
bx %
x$
x#
x"
x!
$end
#5
0!
0'
1&
0(
0#
b0 %
0"
0$
#10
0&
1$
#15
1!
1'
1&
b1 %
1"
0$
#20
0!
0'
0&
1$
#25
1&
1#
b10 %
0"
0$
#30
1!
0&
1(
1$
#35
1'
1!
1&
0(
b11 %
1"
0$
#40
0'
0&
1(
1$
